<?xml version='1.0' encoding='utf-8'?><m:page id='50d3b08c-b5ef-45dc-b73f-0dd063d7766d' xmlns='http://www.w3.org/1999/xhtml' title='Page Title' class='layout-atlas layout-atlas-phone' xmlns:m='http://schemas.mendix.com/forms/1.0'><m:layouts><m:layout path='Atlas_UI_Resources/Phone_Default.layout.xml'></m:layout></m:layouts><m:arguments><m:argument parameterName='fb84d00c-ddc4-4ac5-ac01-b7094028e882'><div data-mendix-id='4_0' class='mx-layoutgrid mx-layoutgrid-fluid container-fluid mx-name-layoutGrid1'><div class='row'><div class='col-md-12'></div></div></div></m:argument><m:argument parameterName='b9f4001c-3b3d-4461-9d29-a676f4744693'></m:argument><m:argument parameterName='01ee5b36-b0c0-4b6b-ab4e-325c4c70311c'></m:argument></m:arguments></m:page>